{
  "descriptionHash": "B19CDFD7E87943E3A7EDCF047F1E0C300380BF29429E16888D1E07BFE6A4C2D081D1CF2EB36D2150110ACE623E6DF5737DCC56DB8A06669911E34CB74C03FE01",
  "descriptionLocation": "../../msgraph-metadata/clean_v10_openapi/openapi.yaml",
  "lockFileVersion": "1.0.0",
  "kiotaVersion": "1.13.0",
  "clientClassName": "BaseGraphClient",
  "clientNamespaceName": "Microsoft\\Graph\\Generated",
  "language": "PHP",
  "usesBackingStore": true,
  "excludeBackwardCompatible": false,
  "includeAdditionalData": true,
  "serializers": [
    "Microsoft.Kiota.Serialization.Json.JsonSerializationWriterFactory",
    "Microsoft.Kiota.Serialization.Text.TextSerializationWriterFactory",
    "Microsoft.Kiota.Serialization.Form.FormSerializationWriterFactory",
    "Microsoft.Kiota.Serialization.Multipart.MultipartSerializationWriterFactory"
  ],
  "deserializers": [
    "Microsoft.Kiota.Serialization.Json.JsonParseNodeFactory",
    "Microsoft.Kiota.Serialization.Text.TextParseNodeFactory",
    "Microsoft.Kiota.Serialization.Form.FormParseNodeFactory"
  ],
  "structuredMimeTypes": [
    "application/json",
    "text/plain;q=0.9",
    "application/x-www-form-urlencoded;q=0.2",
    "multipart/form-data;q=0.1"
  ],
  "includePatterns": [],
  "excludePatterns": [
    "/me",
    "/me/**"
  ],
  "disabledValidationRules": []
}