{
  "descriptionHash": "A6D4D3C6A6ED9A57C4ED9F1D3AED728561CE6A8684D2C8CD494417BFBC1BDC0EC688BB29F5C12E12B0F828D91213F2E5DB6C7F1324B29D17FCAD02136F98C54C",
  "descriptionLocation": "/mnt/vss/_work/1/s/msgraph-metadata/clean_v10_openapi/openapi.yaml",
  "lockFileVersion": "1.0.0",
  "kiotaVersion": "1.7.0",
  "clientClassName": "BaseGraphClient",
  "clientNamespaceName": "Microsoft\\Graph\\Generated",
  "language": "PHP",
  "usesBackingStore": true,
  "excludeBackwardCompatible": false,
  "includeAdditionalData": true,
  "serializers": [
    "Microsoft.Kiota.Serialization.Json.JsonSerializationWriterFactory",
    "Microsoft.Kiota.Serialization.Text.TextSerializationWriterFactory",
    "Microsoft.Kiota.Serialization.Form.FormSerializationWriterFactory",
    "Microsoft.Kiota.Serialization.Multipart.MultipartSerializationWriterFactory"
  ],
  "deserializers": [
    "Microsoft.Kiota.Serialization.Json.JsonParseNodeFactory",
    "Microsoft.Kiota.Serialization.Text.TextParseNodeFactory",
    "Microsoft.Kiota.Serialization.Form.FormParseNodeFactory"
  ],
  "structuredMimeTypes": [
    "application/json",
    "text/plain",
    "application/x-www-form-urlencoded",
    "multipart/form-data"
  ],
  "includePatterns": [],
  "excludePatterns": [
    "/me",
    "/me/**"
  ],
  "disabledValidationRules": []
}