{
  "descriptionHash": "4F06022D5B45031BAB5C100A8706A34FA46122344724E8FCA8C63860D90BF29AC24BE841A1ED2D972C817F599F3CB3D773FDC21B97C78F4BD30527C351DF0259",
  "descriptionLocation": "../../msgraph-metadata/clean_v10_openapi/openapi.yaml",
  "lockFileVersion": "1.0.0",
  "kiotaVersion": "1.30.0",
  "clientClassName": "BaseGraphClient",
  "typeAccessModifier": "Public",
  "clientNamespaceName": "Microsoft\\Graph\\Generated",
  "language": "PHP",
  "usesBackingStore": true,
  "excludeBackwardCompatible": false,
  "includeAdditionalData": true,
  "disableSSLValidation": false,
  "serializers": [
    "Microsoft.Kiota.Serialization.Json.JsonSerializationWriterFactory",
    "Microsoft.Kiota.Serialization.Text.TextSerializationWriterFactory",
    "Microsoft.Kiota.Serialization.Form.FormSerializationWriterFactory",
    "Microsoft.Kiota.Serialization.Multipart.MultipartSerializationWriterFactory"
  ],
  "deserializers": [
    "Microsoft.Kiota.Serialization.Json.JsonParseNodeFactory",
    "Microsoft.Kiota.Serialization.Text.TextParseNodeFactory",
    "Microsoft.Kiota.Serialization.Form.FormParseNodeFactory"
  ],
  "structuredMimeTypes": [
    "application/json",
    "text/plain;q=0.9",
    "application/x-www-form-urlencoded;q=0.2",
    "multipart/form-data;q=0.1"
  ],
  "includePatterns": [],
  "excludePatterns": [
    "/me",
    "/me/**",
    "/copilot",
    "/copilot/**"
  ],
  "disabledValidationRules": []
}